LICENSE
MANIFEST.in
setup.py
django_urli18n.egg-info/PKG-INFO
django_urli18n.egg-info/SOURCES.txt
django_urli18n.egg-info/dependency_links.txt
django_urli18n.egg-info/top_level.txt
urli18n/__init__.py
urli18n/app_settings.py
urli18n/middleware.py
urli18n/models.py
urli18n/utils.py
urli18n/templatetags/__init__.py
urli18n/templatetags/urli18n_tags.py
urli18n/tests/__init__.py
urli18n/tests/urls.py
urli18n/tests/views.py